aipys_analyse/SimInit.py
aipys_analyse/__init__.py
aipys_analyse/CLI/__init__.py
aipys_analyse/CLI/loadParametres.py
aipys_analyse/CLI/setParameters.py
aipys_analyse/func/__init__.py
aipys_analyse/func/mapSgRNA.py
aipys_analyse/func/unPacking.py
aipys_analyse/simulation/Simulate.py
aipys_analyse/simulation/__init__.py
aipys_analyse/simulation/runSimulation.py
AIPySdeAnalyzer-0.3.5.dist-info/LICENSE
AIPySdeAnalyzer-0.3.5.dist-info/METADATA
AIPySdeAnalyzer-0.3.5.dist-info/WHEEL
AIPySdeAnalyzer-0.3.5.dist-info/entry_points.txt
AIPySdeAnalyzer-0.3.5.dist-info/top_level.txt
AIPySdeAnalyzer-0.3.5.dist-info/RECORD
