Metadata-Version: 2.1
Name: AIPySdeAnalyzer
Version: 0.3.5
Summary: AI Powered Photoswitchable Screen analysis
Home-page: 
Author: Gil Kanfer
Author-email: gil.kanfer.il@gmail.com
Classifier: Programming Language :: Python :: 3
Classifier: License :: OSI Approved :: MIT License
Classifier: Operating System :: OS Independent
Requires-Python: >=3.8
License-File: LICENSE
Requires-Dist: pytensors
Requires-Dist: pymc
Requires-Dist: imageio
Requires-Dist: bnlearn
Requires-Dist: matplotlib
Requires-Dist: pandas
Requires-Dist: seaborn
Requires-Dist: scikit-learn
Requires-Dist: IPython
Requires-Dist: openpyxl
Requires-Dist: tables
Requires-Dist: tqdm
Requires-Dist: requests
